CHANGELOG.rst
MANIFEST.in
README.rst
setup.py
logbin/__init__.py
logbin/__main__.py
logbin/handlers.py
logbin.egg-info/PKG-INFO
logbin.egg-info/SOURCES.txt
logbin.egg-info/dependency_links.txt
logbin.egg-info/not-zip-safe
logbin.egg-info/requires.txt
logbin.egg-info/top_level.txt