Metadata-Version: 1.1
Name: logbin
Version: 0.1a
Summary: UNKNOWN
Home-page: UNKNOWN
Author: Samuele Santi
Author-email: redshadow@hackzine.org
License: BSD License
Platform: UNKNOWN
Classifier: License :: OSI Approved :: BSD License
Classifier: Development Status :: 3 - Alpha
Classifier: Programming Language :: Python :: 2.6
Classifier: Programming Language :: Python :: 2.7
